unit_parse/__init__.py
unit_parse/classification.py
unit_parse/config.py
unit_parse/core.py
unit_parse/logger.py
unit_parse/main.py
unit_parse/pre_processing_multiple.py
unit_parse/pre_processing_substitution.py
unit_parse/py.typed
unit_parse/reduce_quantities.py
unit_parse/utils.py
unit_parse/support_files/dictionary.txt
unit_parse-0.1.12.dist-info/licenses/LICENSE.txt
unit_parse-0.1.12.dist-info/METADATA
unit_parse-0.1.12.dist-info/WHEEL
unit_parse-0.1.12.dist-info/top_level.txt
unit_parse-0.1.12.dist-info/RECORD
