Metadata-Version: 2.4
Name: unit_parse
Version: 0.1.12
Summary: Parse units from strings. From mess to order!
Home-page: https://github.com/dylanwal/unit_parse
Author: Dylan Walsh
License: BSD
Platform: any
Classifier: License :: OSI Approved :: BSD License
Classifier: Programming Language :: Python :: 3
Classifier: Programming Language :: Python :: 3 :: Only
Classifier: Programming Language :: Python :: 3.10
Requires-Python: >=3.10
License-File: LICENSE.txt
Requires-Dist: pint>=0.24.1
Provides-Extra: testing
Requires-Dist: pytest>=6.0; extra == "testing"
Requires-Dist: pytest-cov>=2.0; extra == "testing"
Requires-Dist: mypy>=0.910; extra == "testing"
Requires-Dist: flake8>=3.9; extra == "testing"
Dynamic: license-file
